unzipwalk
