Metadata-Version: 2.4
Name: unzipwalk
Version: 1.8.1
Summary: Recursively walk into directories and archives
Author-email: Hauke D <haukex@zero-g.net>
License-Expression: LGPL-3.0-or-later
Project-URL: Repository, https://github.com/haukex/unzipwalk
Project-URL: Bug Tracker, https://github.com/haukex/unzipwalk/issues
Project-URL: Changelog, https://github.com/haukex/unzipwalk/blob/main/CHANGELOG.md
Classifier: Programming Language :: Python :: 3
Classifier: Programming Language :: Python :: 3.10
Classifier: Programming Language :: Python :: 3.11
Classifier: Programming Language :: Python :: 3.12
Classifier: Programming Language :: Python :: 3.13
Classifier: Programming Language :: Python :: 3.14
Classifier: Development Status :: 5 - Production/Stable
Classifier: Operating System :: POSIX
Classifier: Operating System :: Unix
Classifier: Operating System :: Microsoft :: Windows
Classifier: Operating System :: MacOS :: MacOS X
Classifier: Topic :: Software Development :: Libraries
Classifier: Topic :: System :: Archiving
Requires-Python: >=3.10
License-File: LICENSE.txt
Requires-Dist: igbpyutils>=0.8.0
Provides-Extra: 7z
Requires-Dist: py7zr>=0.22.0; extra == "7z"
Dynamic: license-file
